mtxt/__init__.py
mtxt/mtxt.cpython-310-darwin.so
mtxt-0.9.0.dist-info/METADATA
mtxt-0.9.0.dist-info/WHEEL
mtxt-0.9.0.dist-info/licenses/LICENSE-APACHE
mtxt-0.9.0.dist-info/licenses/LICENSE-MIT
python/mtxt/__init__.pyi
python/mtxt/py.typed
mtxt-0.9.0.dist-info/RECORD
