Metadata-Version: 2.4
Name: mtxt
Version: 0.9.0
Classifier: Development Status :: 4 - Beta
Classifier: Intended Audience :: Developers
Classifier: Intended Audience :: Science/Research
Classifier: License :: OSI Approved :: MIT License
Classifier: Programming Language :: Rust
Classifier: Programming Language :: Python :: 3
Classifier: Programming Language :: Python :: 3.8
Classifier: Programming Language :: Python :: 3.9
Classifier: Programming Language :: Python :: 3.10
Classifier: Programming Language :: Python :: 3.11
Classifier: Programming Language :: Python :: 3.12
Classifier: Topic :: Multimedia :: Sound/Audio
Classifier: Topic :: Software Development :: Libraries
License-File: LICENSE-APACHE
License-File: LICENSE-MIT
Summary: MTXT Music Text Format - Python bindings
Keywords: mtxt,music,midi,text,format
Author: Sven Hollowell
Author-email: Dani Biró <danipro93@gmail.com>
License: MIT
Requires-Python: >=3.8
Project-URL: Homepage, https://github.com/supersational/mtxt/tree/python-lib
Project-URL: Repository, https://github.com/supersational/mtxt/tree/python-lib
